jsontab/__init__.py
jsontab/jsontab.py
jsontab-0.0.9.dist-info/LICENSE
jsontab-0.0.9.dist-info/METADATA
jsontab-0.0.9.dist-info/WHEEL
jsontab-0.0.9.dist-info/top_level.txt
jsontab-0.0.9.dist-info/RECORD
