Metadata-Version: 2.1
Name: jsontab
Version: 0.0.9
Summary: Agnostically load JSON or tabular data
Home-page: https://github.com/anthony-aylward/jsontab.git
Author: Anthony Aylward
Author-email: aaylward@eng.ucsd.edu
License: UNKNOWN
Platform: UNKNOWN
Classifier: Programming Language :: Python :: 3
Classifier: License :: OSI Approved :: MIT License
Classifier: Operating System :: OS Independent
Requires-Dist: pandas
